sandbox_fusion/__init__.py
sandbox_fusion/async_client.py
sandbox_fusion/client.py
sandbox_fusion/common.py
sandbox_fusion/config.py
sandbox_fusion/models.py
sandbox_fusion-0.3.7.dist-info/LICENSE
sandbox_fusion-0.3.7.dist-info/METADATA
sandbox_fusion-0.3.7.dist-info/WHEEL
sandbox_fusion-0.3.7.dist-info/top_level.txt
sandbox_fusion-0.3.7.dist-info/RECORD
